{
    "name": "tournament_241",
    "start_date": "2015-10-21",
    "end_date": "2015-11-16",
    "games": {
        "tour_1": [
            {
                "white": "Zheng Jianyuan",
                "black": "Zhang Yanying",
                "date": "2015-10-21",
                "result": 0.5,
                "id": "tournament_241_1"
            },
            {
                "white": "Li Shuchu",
                "black": "Li Youhui",
                "date": "2015-10-21",
                "result": 0.5,
                "id": "tournament_241_2"
            },
            {
                "white": "Liang Meiqiang",
                "black": "Hao Xing",
                "date": "2015-10-21",
                "result": 0,
                "id": "tournament_241_3"
            },
            {
                "white": "Huang Xing",
                "black": "Wu Yishun",
                "date": "2015-10-21",
                "result": 1,
                "id": "tournament_241_4"
            },
            {
                "white": "Feng Xiongmin",
                "black": "He Sipei",
                "date": "2015-10-21",
                "result": 1,
                "id": "tournament_241_5"
            },
            {
                "white": "Hu Qihong",
                "black": "Chen Chun",
                "date": "2015-10-21",
                "result": 1,
                "id": "tournament_241_6"
            },
            {
                "white": "Hao Yong",
                "black": "Yang Jianxia",
                "date": "2015-10-21",
                "result": 0.5,
                "id": "tournament_241_7"
            },
            {
                "white": "Hu Shoubiao",
                "black": "Li Linhua",
                "date": "2015-10-21",
                "result": 1,
                "id": "tournament_241_8"
            },
            {
                "white": "Li Songjiang",
                "black": "Zhao Junzhong",
                "date": "2015-10-21",
                "result": 1,
                "id": "tournament_241_9"
            },
            {
                "white": "Zhu Xiuyang",
                "black": "Ma Chaofeng",
                "date": "2015-10-21",
                "result": 1,
                "id": "tournament_241_10"
            },
            {
                "white": "Liu Biyan",
                "black": "Wang Tianbo",
                "date": "2015-10-21",
                "result": 0.5,
                "id": "tournament_241_11"
            },
            {
                "white": "Bai Xiaoan",
                "black": "Xu Baolong",
                "date": "2015-10-21",
                "result": 1,
                "id": "tournament_241_12"
            },
            {
                "white": "Ji Wenfu",
                "black": "Li Jun",
                "date": "2015-10-21",
                "result": 0.5,
                "id": "tournament_241_13"
            },
            {
                "white": "Hu Jianping",
                "black": "Li Hai",
                "date": "2015-10-21",
                "result": 0,
                "id": "tournament_241_14"
            },
            {
                "white": "Zhu Zixin",
                "black": "Li Tengtian",
                "date": "2015-10-21",
                "result": 1,
                "id": "tournament_241_15"
            },
            {
                "white": "Lai Zhenen",
                "black": "Huang Shuchu",
                "date": "2015-10-21",
                "result": 0.5,
                "id": "tournament_241_16"
            },
            {
                "white": "Lin Xianzhi",
                "black": "Chen Xiangke",
                "date": "2015-10-21",
                "result": 0.5,
                "id": "tournament_241_17"
            },
            {
                "white": "Hao Hualin",
                "black": "Zheng Xuanzhen",
                "date": "2015-10-21",
                "result": 0,
                "id": "tournament_241_18"
            },
            {
                "white": "Fu Qingfang",
                "black": "Li Jianfang",
                "date": "2015-10-21",
                "result": 0.5,
                "id": "tournament_241_19"
            },
            {
                "white": "Deng Zhenhua",
                "black": "Qiang Haitian",
                "date": "2015-10-21",
                "result": 0.5,
                "id": "tournament_241_20"
            },
            {
                "white": "Song Shuaihui",
                "black": "Xu Ming",
                "date": "2015-10-21",
                "result": 0.5,
                "id": "tournament_241_21"
            },
            {
                "white": "Yang Jing",
                "black": "Zhang Xu",
                "date": "2015-10-21",
                "result": 0.5,
                "id": "tournament_241_22"
            },
            {
                "white": "Liu Qinxin",
                "black": "Liu Kunhan",
                "date": "2015-10-21",
                "result": 0.5,
                "id": "tournament_241_23"
            },
            {
                "white": "Yan Sijun",
                "black": "Yin Fang",
                "date": "2015-10-21",
                "result": 1,
                "id": "tournament_241_24"
            },
            {
                "white": "Lin Haopeng",
                "black": "Qiao Hongqi",
                "date": "2015-10-21",
                "result": 1,
                "id": "tournament_241_25"
            },
            {
                "white": "Meng Fangquan",
                "black": "Xie Libo",
                "date": "2015-10-21",
                "result": 0,
                "id": "tournament_241_26"
            },
            {
                "white": "Yang Yuxian",
                "black": "Guo Deji",
                "date": "2015-10-21",
                "result": 0.5,
                "id": "tournament_241_27"
            },
            {
                "white": "Liu Xian",
                "black": "Hu Youbiao",
                "date": "2015-10-21",
                "result": 0.5,
                "id": "tournament_241_28"
            },
            {
                "white": "Yu Ping",
                "black": "Liang Xiaowei",
                "date": "2015-10-21",
                "result": 0.5,
                "id": "tournament_241_29"
            },
            {
                "white": "Li Wenzi",
                "black": "Wang Jiangji",
                "date": "2015-10-21",
                "result": 0.5,
                "id": "tournament_241_30"
            }
        ],
        "tour_2": [
            {
                "white": "Hao Xing",
                "black": "Huang Xing",
                "date": "2015-10-23",
                "result": 0,
                "id": "tournament_241_31"
            },
            {
                "white": "Li Hai",
                "black": "Feng Xiongmin",
                "date": "2015-10-23",
                "result": 0.5,
                "id": "tournament_241_32"
            },
            {
                "white": "Zheng Xuanzhen",
                "black": "Hu Qihong",
                "date": "2015-10-23",
                "result": 0.5,
                "id": "tournament_241_33"
            },
            {
                "white": "Xie Libo",
                "black": "Hu Shoubiao",
                "date": "2015-10-23",
                "result": 1,
                "id": "tournament_241_34"
            },
            {
                "white": "Zhang Yanying",
                "black": "Li Songjiang",
                "date": "2015-10-23",
                "result": 0,
                "id": "tournament_241_35"
            },
            {
                "white": "Li Youhui",
                "black": "Zhu Xiuyang",
                "date": "2015-10-23",
                "result": 0.5,
                "id": "tournament_241_36"
            },
            {
                "white": "Yang Jianxia",
                "black": "Bai Xiaoan",
                "date": "2015-10-23",
                "result": 0,
                "id": "tournament_241_37"
            },
            {
                "white": "Wang Tianbo",
                "black": "Zhu Zixin",
                "date": "2015-10-23",
                "result": 0.5,
                "id": "tournament_241_38"
            },
            {
                "white": "Li Jun",
                "black": "Yan Sijun",
                "date": "2015-10-23",
                "result": 1,
                "id": "tournament_241_39"
            },
            {
                "white": "Huang Shuchu",
                "black": "Lin Haopeng",
                "date": "2015-10-23",
                "result": 0,
                "id": "tournament_241_40"
            },
            {
                "white": "Chen Xiangke",
                "black": "Zheng Jianyuan",
                "date": "2015-10-23",
                "result": 1,
                "id": "tournament_241_41"
            },
            {
                "white": "Li Jianfang",
                "black": "Li Shuchu",
                "date": "2015-10-23",
                "result": 0,
                "id": "tournament_241_42"
            },
            {
                "white": "Qiang Haitian",
                "black": "Hao Yong",
                "date": "2015-10-23",
                "result": 1,
                "id": "tournament_241_43"
            },
            {
                "white": "Xu Ming",
                "black": "Liu Biyan",
                "date": "2015-10-23",
                "result": 1,
                "id": "tournament_241_44"
            },
            {
                "white": "Zhang Xu",
                "black": "Ji Wenfu",
                "date": "2015-10-23",
                "result": 0.5,
                "id": "tournament_241_45"
            },
            {
                "white": "Liu Kunhan",
                "black": "Lai Zhenen",
                "date": "2015-10-23",
                "result": 0.5,
                "id": "tournament_241_46"
            },
            {
                "white": "Guo Deji",
                "black": "Lin Xianzhi",
                "date": "2015-10-23",
                "result": 1,
                "id": "tournament_241_47"
            },
            {
                "white": "Hu Youbiao",
                "black": "Fu Qingfang",
                "date": "2015-10-23",
                "result": 0.5,
                "id": "tournament_241_48"
            },
            {
                "white": "Liang Xiaowei",
                "black": "Deng Zhenhua",
                "date": "2015-10-23",
                "result": 0,
                "id": "tournament_241_49"
            },
            {
                "white": "Wang Jiangji",
                "black": "Song Shuaihui",
                "date": "2015-10-23",
                "result": 0.5,
                "id": "tournament_241_50"
            },
            {
                "white": "Wu Yishun",
                "black": "Yang Jing",
                "date": "2015-10-23",
                "result": 1,
                "id": "tournament_241_51"
            },
            {
                "white": "He Sipei",
                "black": "Liu Qinxin",
                "date": "2015-10-23",
                "result": 0,
                "id": "tournament_241_52"
            },
            {
                "white": "Chen Chun",
                "black": "Yang Yuxian",
                "date": "2015-10-23",
                "result": 1,
                "id": "tournament_241_53"
            },
            {
                "white": "Li Linhua",
                "black": "Liu Xian",
                "date": "2015-10-23",
                "result": 0,
                "id": "tournament_241_54"
            },
            {
                "white": "Zhao Junzhong",
                "black": "Yu Ping",
                "date": "2015-10-23",
                "result": 0,
                "id": "tournament_241_55"
            },
            {
                "white": "Ma Chaofeng",
                "black": "Li Wenzi",
                "date": "2015-10-23",
                "result": 1,
                "id": "tournament_241_56"
            },
            {
                "white": "Xu Baolong",
                "black": "Liang Meiqiang",
                "date": "2015-10-23",
                "result": 0,
                "id": "tournament_241_57"
            },
            {
                "white": "Li Tengtian",
                "black": "Hu Jianping",
                "date": "2015-10-23",
                "result": 0.5,
                "id": "tournament_241_58"
            },
            {
                "white": "Yin Fang",
                "black": "Hao Hualin",
                "date": "2015-10-23",
                "result": 0,
                "id": "tournament_241_59"
            },
            {
                "white": "Qiao Hongqi",
                "black": "Meng Fangquan",
                "date": "2015-10-23",
                "result": 0,
                "id": "tournament_241_60"
            }
        ],
        "tour_3": [
            {
                "white": "Huang Xing",
                "black": "Xie Libo",
                "date": "2015-10-25",
                "result": 1,
                "id": "tournament_241_61"
            },
            {
                "white": "Li Songjiang",
                "black": "Li Hai",
                "date": "2015-10-25",
                "result": 0,
                "id": "tournament_241_62"
            },
            {
                "white": "Bai Xiaoan",
                "black": "Zheng Xuanzhen",
                "date": "2015-10-25",
                "result": 0,
                "id": "tournament_241_63"
            },
            {
                "white": "Lin Haopeng",
                "black": "Li Jun",
                "date": "2015-10-25",
                "result": 0.5,
                "id": "tournament_241_64"
            },
            {
                "white": "Feng Xiongmin",
                "black": "Chen Xiangke",
                "date": "2015-10-25",
                "result": 1,
                "id": "tournament_241_65"
            },
            {
                "white": "Hu Qihong",
                "black": "Qiang Haitian",
                "date": "2015-10-25",
                "result": 0,
                "id": "tournament_241_66"
            },
            {
                "white": "Zhu Xiuyang",
                "black": "Xu Ming",
                "date": "2015-10-25",
                "result": 1,
                "id": "tournament_241_67"
            },
            {
                "white": "Zhu Zixin",
                "black": "Guo Deji",
                "date": "2015-10-25",
                "result": 0.5,
                "id": "tournament_241_68"
            },
            {
                "white": "Li Shuchu",
                "black": "Hao Xing",
                "date": "2015-10-25",
                "result": 0,
                "id": "tournament_241_69"
            },
            {
                "white": "Deng Zhenhua",
                "black": "Li Youhui",
                "date": "2015-10-25",
                "result": 1,
                "id": "tournament_241_70"
            },
            {
                "white": "Liu Qinxin",
                "black": "Wang Tianbo",
                "date": "2015-10-25",
                "result": 1,
                "id": "tournament_241_71"
            },
            {
                "white": "Liu Xian",
                "black": "Zhang Xu",
                "date": "2015-10-25",
                "result": 1,
                "id": "tournament_241_72"
            },
            {
                "white": "Yu Ping",
                "black": "Liu Kunhan",
                "date": "2015-10-25",
                "result": 1,
                "id": "tournament_241_73"
            },
            {
                "white": "Hu Shoubiao",
                "black": "Hu Youbiao",
                "date": "2015-10-25",
                "result": 0.5,
                "id": "tournament_241_74"
            },
            {
                "white": "Yan Sijun",
                "black": "Wang Jiangji",
                "date": "2015-10-25",
                "result": 0.5,
                "id": "tournament_241_75"
            },
            {
                "white": "Ji Wenfu",
                "black": "Wu Yishun",
                "date": "2015-10-25",
                "result": 0.5,
                "id": "tournament_241_76"
            },
            {
                "white": "Lai Zhenen",
                "black": "Chen Chun",
                "date": "2015-10-25",
                "result": 1,
                "id": "tournament_241_77"
            },
            {
                "white": "Fu Qingfang",
                "black": "Ma Chaofeng",
                "date": "2015-10-25",
                "result": 0.5,
                "id": "tournament_241_78"
            },
            {
                "white": "Song Shuaihui",
                "black": "Zhang Yanying",
                "date": "2015-10-25",
                "result": 0,
                "id": "tournament_241_79"
            },
            {
                "white": "Liang Meiqiang",
                "black": "Yang Jianxia",
                "date": "2015-10-25",
                "result": 0.5,
                "id": "tournament_241_80"
            },
            {
                "white": "Hao Hualin",
                "black": "Huang Shuchu",
                "date": "2015-10-25",
                "result": 1,
                "id": "tournament_241_81"
            },
            {
                "white": "Meng Fangquan",
                "black": "Li Jianfang",
                "date": "2015-10-25",
                "result": 0,
                "id": "tournament_241_82"
            },
            {
                "white": "Zheng Jianyuan",
                "black": "Liang Xiaowei",
                "date": "2015-10-25",
                "result": 1,
                "id": "tournament_241_83"
            },
            {
                "white": "Hao Yong",
                "black": "Li Tengtian",
                "date": "2015-10-25",
                "result": 0.5,
                "id": "tournament_241_84"
            },
            {
                "white": "Liu Biyan",
                "black": "He Sipei",
                "date": "2015-10-25",
                "result": 0.5,
                "id": "tournament_241_85"
            },
            {
                "white": "Lin Xianzhi",
                "black": "Li Linhua",
                "date": "2015-10-25",
                "result": 0.5,
                "id": "tournament_241_86"
            },
            {
                "white": "Yang Jing",
                "black": "Zhao Junzhong",
                "date": "2015-10-25",
                "result": 0.5,
                "id": "tournament_241_87"
            },
            {
                "white": "Yang Yuxian",
                "black": "Xu Baolong",
                "date": "2015-10-25",
                "result": 0,
                "id": "tournament_241_88"
            },
            {
                "white": "Li Wenzi",
                "black": "Qiao Hongqi",
                "date": "2015-10-25",
                "result": 1,
                "id": "tournament_241_89"
            },
            {
                "white": "Hu Jianping",
                "black": "Yin Fang",
                "date": "2015-10-25",
                "result": 1,
                "id": "tournament_241_90"
            }
        ],
        "tour_4": [
            {
                "white": "Li Hai",
                "black": "Huang Xing",
                "date": "2015-10-27",
                "result": 0.5,
                "id": "tournament_241_91"
            },
            {
                "white": "Zheng Xuanzhen",
                "black": "Lin Haopeng",
                "date": "2015-10-27",
                "result": 1,
                "id": "tournament_241_92"
            },
            {
                "white": "Qiang Haitian",
                "black": "Feng Xiongmin",
                "date": "2015-10-27",
                "result": 1,
                "id": "tournament_241_93"
            },
            {
                "white": "Xie Libo",
                "black": "Zhu Xiuyang",
                "date": "2015-10-27",
                "result": 0.5,
                "id": "tournament_241_94"
            },
            {
                "white": "Li Jun",
                "black": "Deng Zhenhua",
                "date": "2015-10-27",
                "result": 0,
                "id": "tournament_241_95"
            },
            {
                "white": "Guo Deji",
                "black": "Liu Qinxin",
                "date": "2015-10-27",
                "result": 1,
                "id": "tournament_241_96"
            },
            {
                "white": "Hao Xing",
                "black": "Liu Xian",
                "date": "2015-10-27",
                "result": 0.5,
                "id": "tournament_241_97"
            },
            {
                "white": "Chen Xiangke",
                "black": "Yu Ping",
                "date": "2015-10-27",
                "result": 0.5,
                "id": "tournament_241_98"
            },
            {
                "white": "Xu Ming",
                "black": "Li Songjiang",
                "date": "2015-10-27",
                "result": 0.5,
                "id": "tournament_241_99"
            },
            {
                "white": "Hu Youbiao",
                "black": "Bai Xiaoan",
                "date": "2015-10-27",
                "result": 1,
                "id": "tournament_241_100"
            },
            {
                "white": "Wang Jiangji",
                "black": "Zhu Zixin",
                "date": "2015-10-27",
                "result": 0,
                "id": "tournament_241_101"
            },
            {
                "white": "Wu Yishun",
                "black": "Lai Zhenen",
                "date": "2015-10-27",
                "result": 1,
                "id": "tournament_241_102"
            },
            {
                "white": "Ma Chaofeng",
                "black": "Hao Hualin",
                "date": "2015-10-27",
                "result": 1,
                "id": "tournament_241_103"
            },
            {
                "white": "Zhang Yanying",
                "black": "Hu Qihong",
                "date": "2015-10-27",
                "result": 0,
                "id": "tournament_241_104"
            },
            {
                "white": "Wang Tianbo",
                "black": "Li Shuchu",
                "date": "2015-10-27",
                "result": 0,
                "id": "tournament_241_105"
            },
            {
                "white": "Li Jianfang",
                "black": "Hu Shoubiao",
                "date": "2015-10-27",
                "result": 1,
                "id": "tournament_241_106"
            },
            {
                "white": "Li Youhui",
                "black": "Yan Sijun",
                "date": "2015-10-27",
                "result": 0.5,
                "id": "tournament_241_107"
            },
            {
                "white": "Liu Kunhan",
                "black": "Ji Wenfu",
                "date": "2015-10-27",
                "result": 0.5,
                "id": "tournament_241_108"
            },
            {
                "white": "Zhang Xu",
                "black": "Fu Qingfang",
                "date": "2015-10-27",
                "result": 0.5,
                "id": "tournament_241_109"
            },
            {
                "white": "Chen Chun",
                "black": "Liang Meiqiang",
                "date": "2015-10-27",
                "result": 1,
                "id": "tournament_241_110"
            },
            {
                "white": "Yang Jianxia",
                "black": "Zheng Jianyuan",
                "date": "2015-10-27",
                "result": 0,
                "id": "tournament_241_111"
            },
            {
                "white": "Li Tengtian",
                "black": "Li Wenzi",
                "date": "2015-10-27",
                "result": 0.5,
                "id": "tournament_241_112"
            },
            {
                "white": "Xu Baolong",
                "black": "Hu Jianping",
                "date": "2015-10-27",
                "result": 0.5,
                "id": "tournament_241_113"
            },
            {
                "white": "Huang Shuchu",
                "black": "Song Shuaihui",
                "date": "2015-10-27",
                "result": 0.5,
                "id": "tournament_241_114"
            },
            {
                "white": "Liang Xiaowei",
                "black": "Meng Fangquan",
                "date": "2015-10-27",
                "result": 1,
                "id": "tournament_241_115"
            },
            {
                "white": "He Sipei",
                "black": "Hao Yong",
                "date": "2015-10-27",
                "result": 0,
                "id": "tournament_241_116"
            },
            {
                "white": "Li Linhua",
                "black": "Liu Biyan",
                "date": "2015-10-27",
                "result": 1,
                "id": "tournament_241_117"
            },
            {
                "white": "Zhao Junzhong",
                "black": "Lin Xianzhi",
                "date": "2015-10-27",
                "result": 1,
                "id": "tournament_241_118"
            },
            {
                "white": "Qiao Hongqi",
                "black": "Yang Jing",
                "date": "2015-10-27",
                "result": 0.5,
                "id": "tournament_241_119"
            },
            {
                "white": "Yin Fang",
                "black": "Yang Yuxian",
                "date": "2015-10-27",
                "result": 0,
                "id": "tournament_241_120"
            }
        ],
        "tour_5": [
            {
                "white": "Huang Xing",
                "black": "Zheng Xuanzhen",
                "date": "2015-10-29",
                "result": 1,
                "id": "tournament_241_121"
            },
            {
                "white": "Deng Zhenhua",
                "black": "Li Hai",
                "date": "2015-10-29",
                "result": 1,
                "id": "tournament_241_122"
            },
            {
                "white": "Zhu Xiuyang",
                "black": "Qiang Haitian",
                "date": "2015-10-29",
                "result": 0.5,
                "id": "tournament_241_123"
            },
            {
                "white": "Liu Xian",
                "black": "Guo Deji",
                "date": "2015-10-29",
                "result": 1,
                "id": "tournament_241_124"
            },
            {
                "white": "Yu Ping",
                "black": "Xie Libo",
                "date": "2015-10-29",
                "result": 0.5,
                "id": "tournament_241_125"
            },
            {
                "white": "Zhu Zixin",
                "black": "Hao Xing",
                "date": "2015-10-29",
                "result": 1,
                "id": "tournament_241_126"
            },
            {
                "white": "Lin Haopeng",
                "black": "Hu Youbiao",
                "date": "2015-10-29",
                "result": 1,
                "id": "tournament_241_127"
            },
            {
                "white": "Feng Xiongmin",
                "black": "Wu Yishun",
                "date": "2015-10-29",
                "result": 1,
                "id": "tournament_241_128"
            },
            {
                "white": "Liu Qinxin",
                "black": "Ma Chaofeng",
                "date": "2015-10-29",
                "result": 0.5,
                "id": "tournament_241_129"
            },
            {
                "white": "Li Songjiang",
                "black": "Li Jianfang",
                "date": "2015-10-29",
                "result": 0.5,
                "id": "tournament_241_130"
            },
            {
                "white": "Hu Qihong",
                "black": "Li Jun",
                "date": "2015-10-29",
                "result": 1,
                "id": "tournament_241_131"
            },
            {
                "white": "Li Shuchu",
                "black": "Chen Xiangke",
                "date": "2015-10-29",
                "result": 1,
                "id": "tournament_241_132"
            },
            {
                "white": "Zheng Jianyuan",
                "black": "Xu Ming",
                "date": "2015-10-29",
                "result": 0.5,
                "id": "tournament_241_133"
            },
            {
                "white": "Bai Xiaoan",
                "black": "Chen Chun",
                "date": "2015-10-29",
                "result": 0.5,
                "id": "tournament_241_134"
            },
            {
                "white": "Lai Zhenen",
                "black": "Wang Jiangji",
                "date": "2015-10-29",
                "result": 1,
                "id": "tournament_241_135"
            },
            {
                "white": "Hao Hualin",
                "black": "Zhang Yanying",
                "date": "2015-10-29",
                "result": 1,
                "id": "tournament_241_136"
            },
            {
                "white": "Yan Sijun",
                "black": "Zhang Xu",
                "date": "2015-10-29",
                "result": 0.5,
                "id": "tournament_241_137"
            },
            {
                "white": "Ji Wenfu",
                "black": "Li Youhui",
                "date": "2015-10-29",
                "result": 0.5,
                "id": "tournament_241_138"
            },
            {
                "white": "Fu Qingfang",
                "black": "Liu Kunhan",
                "date": "2015-10-29",
                "result": 1,
                "id": "tournament_241_139"
            },
            {
                "white": "Li Wenzi",
                "black": "Xu Baolong",
                "date": "2015-10-29",
                "result": 1,
                "id": "tournament_241_140"
            },
            {
                "white": "Hu Jianping",
                "black": "Liang Xiaowei",
                "date": "2015-10-29",
                "result": 1,
                "id": "tournament_241_141"
            },
            {
                "white": "Hao Yong",
                "black": "Li Linhua",
                "date": "2015-10-29",
                "result": 1,
                "id": "tournament_241_142"
            },
            {
                "white": "Hu Shoubiao",
                "black": "Li Tengtian",
                "date": "2015-10-29",
                "result": 1,
                "id": "tournament_241_143"
            },
            {
                "white": "Liang Meiqiang",
                "black": "Zhao Junzhong",
                "date": "2015-10-29",
                "result": 1,
                "id": "tournament_241_144"
            },
            {
                "white": "Song Shuaihui",
                "black": "Wang Tianbo",
                "date": "2015-10-29",
                "result": 0.5,
                "id": "tournament_241_145"
            },
            {
                "white": "Yang Jing",
                "black": "Yang Jianxia",
                "date": "2015-10-29",
                "result": 0.5,
                "id": "tournament_241_146"
            },
            {
                "white": "Yang Yuxian",
                "black": "Huang Shuchu",
                "date": "2015-10-29",
                "result": 1,
                "id": "tournament_241_147"
            },
            {
                "white": "Meng Fangquan",
                "black": "He Sipei",
                "date": "2015-10-29",
                "result": 0.5,
                "id": "tournament_241_148"
            },
            {
                "white": "Lin Xianzhi",
                "black": "Yin Fang",
                "date": "2015-10-29",
                "result": 0,
                "id": "tournament_241_149"
            },
            {
                "white": "Liu Biyan",
                "black": "Qiao Hongqi",
                "date": "2015-10-29",
                "result": 0.5,
                "id": "tournament_241_150"
            }
        ],
        "tour_6": [
            {
                "white": "Qiang Haitian",
                "black": "Huang Xing",
                "date": "2015-10-31",
                "result": 0.5,
                "id": "tournament_241_151"
            },
            {
                "white": "Zheng Xuanzhen",
                "black": "Deng Zhenhua",
                "date": "2015-10-31",
                "result": 0.5,
                "id": "tournament_241_152"
            },
            {
                "white": "Li Hai",
                "black": "Liu Xian",
                "date": "2015-10-31",
                "result": 0.5,
                "id": "tournament_241_153"
            },
            {
                "white": "Xie Libo",
                "black": "Zhu Zixin",
                "date": "2015-10-31",
                "result": 0.5,
                "id": "tournament_241_154"
            },
            {
                "white": "Guo Deji",
                "black": "Zhu Xiuyang",
                "date": "2015-10-31",
                "result": 1,
                "id": "tournament_241_155"
            },
            {
                "white": "Ma Chaofeng",
                "black": "Yu Ping",
                "date": "2015-10-31",
                "result": 0,
                "id": "tournament_241_156"
            },
            {
                "white": "Li Jianfang",
                "black": "Lin Haopeng",
                "date": "2015-10-31",
                "result": 0.5,
                "id": "tournament_241_157"
            },
            {
                "white": "Hao Xing",
                "black": "Feng Xiongmin",
                "date": "2015-10-31",
                "result": 0,
                "id": "tournament_241_158"
            },
            {
                "white": "Hu Youbiao",
                "black": "Hu Qihong",
                "date": "2015-10-31",
                "result": 0.5,
                "id": "tournament_241_159"
            },
            {
                "white": "Wu Yishun",
                "black": "Li Shuchu",
                "date": "2015-10-31",
                "result": 0,
                "id": "tournament_241_160"
            },
            {
                "white": "Xu Ming",
                "black": "Liu Qinxin",
                "date": "2015-10-31",
                "result": 1,
                "id": "tournament_241_161"
            },
            {
                "white": "Chen Chun",
                "black": "Li Songjiang",
                "date": "2015-10-31",
                "result": 1,
                "id": "tournament_241_162"
            },
            {
                "white": "Li Jun",
                "black": "Zheng Jianyuan",
                "date": "2015-10-31",
                "result": 1,
                "id": "tournament_241_163"
            },
            {
                "white": "Chen Xiangke",
                "black": "Lai Zhenen",
                "date": "2015-10-31",
                "result": 0.5,
                "id": "tournament_241_164"
            },
            {
                "white": "Li Youhui",
                "black": "Hao Hualin",
                "date": "2015-10-31",
                "result": 0.5,
                "id": "tournament_241_165"
            },
            {
                "white": "Wang Jiangji",
                "black": "Fu Qingfang",
                "date": "2015-10-31",
                "result": 0.5,
                "id": "tournament_241_166"
            },
            {
                "white": "Zhang Xu",
                "black": "Li Wenzi",
                "date": "2015-10-31",
                "result": 0.5,
                "id": "tournament_241_167"
            },
            {
                "white": "Zhang Yanying",
                "black": "Hu Jianping",
                "date": "2015-10-31",
                "result": 1,
                "id": "tournament_241_168"
            },
            {
                "white": "Liu Kunhan",
                "black": "Hao Yong",
                "date": "2015-10-31",
                "result": 0,
                "id": "tournament_241_169"
            },
            {
                "white": "Li Tengtian",
                "black": "Bai Xiaoan",
                "date": "2015-10-31",
                "result": 1,
                "id": "tournament_241_170"
            },
            {
                "white": "Xu Baolong",
                "black": "Yan Sijun",
                "date": "2015-10-31",
                "result": 0,
                "id": "tournament_241_171"
            },
            {
                "white": "Liang Xiaowei",
                "black": "Ji Wenfu",
                "date": "2015-10-31",
                "result": 0.5,
                "id": "tournament_241_172"
            },
            {
                "white": "Zhao Junzhong",
                "black": "Hu Shoubiao",
                "date": "2015-10-31",
                "result": 0.5,
                "id": "tournament_241_173"
            },
            {
                "white": "Li Linhua",
                "black": "Liang Meiqiang",
                "date": "2015-10-31",
                "result": 1,
                "id": "tournament_241_174"
            },
            {
                "white": "Wang Tianbo",
                "black": "Yang Yuxian",
                "date": "2015-10-31",
                "result": 0,
                "id": "tournament_241_175"
            },
            {
                "white": "Yang Jianxia",
                "black": "Song Shuaihui",
                "date": "2015-10-31",
                "result": 0,
                "id": "tournament_241_176"
            },
            {
                "white": "He Sipei",
                "black": "Yang Jing",
                "date": "2015-10-31",
                "result": 0.5,
                "id": "tournament_241_177"
            },
            {
                "white": "Yin Fang",
                "black": "Liu Biyan",
                "date": "2015-10-31",
                "result": 1,
                "id": "tournament_241_178"
            },
            {
                "white": "Qiao Hongqi",
                "black": "Lin Xianzhi",
                "date": "2015-10-31",
                "result": 1,
                "id": "tournament_241_179"
            },
            {
                "white": "Huang Shuchu",
                "black": "Meng Fangquan",
                "date": "2015-10-31",
                "result": 1,
                "id": "tournament_241_180"
            }
        ],
        "tour_7": [
            {
                "white": "Huang Xing",
                "black": "Guo Deji",
                "date": "2015-11-02",
                "result": 1,
                "id": "tournament_241_181"
            },
            {
                "white": "Deng Zhenhua",
                "black": "Xie Libo",
                "date": "2015-11-02",
                "result": 0,
                "id": "tournament_241_182"
            },
            {
                "white": "Liu Xian",
                "black": "Qiang Haitian",
                "date": "2015-11-02",
                "result": 0,
                "id": "tournament_241_183"
            },
            {
                "white": "Zhu Zixin",
                "black": "Zheng Xuanzhen",
                "date": "2015-11-02",
                "result": 1,
                "id": "tournament_241_184"
            },
            {
                "white": "Yu Ping",
                "black": "Li Hai",
                "date": "2015-11-02",
                "result": 1,
                "id": "tournament_241_185"
            },
            {
                "white": "Feng Xiongmin",
                "black": "Li Jianfang",
                "date": "2015-11-02",
                "result": 0.5,
                "id": "tournament_241_186"
            },
            {
                "white": "Li Shuchu",
                "black": "Xu Ming",
                "date": "2015-11-02",
                "result": 0.5,
                "id": "tournament_241_187"
            },
            {
                "white": "Lin Haopeng",
                "black": "Chen Chun",
                "date": "2015-11-02",
                "result": 1,
                "id": "tournament_241_188"
            },
            {
                "white": "Hu Qihong",
                "black": "Ma Chaofeng",
                "date": "2015-11-02",
                "result": 1,
                "id": "tournament_241_189"
            },
            {
                "white": "Hao Yong",
                "black": "Hu Youbiao",
                "date": "2015-11-02",
                "result": 0,
                "id": "tournament_241_190"
            },
            {
                "white": "Zhu Xiuyang",
                "black": "Li Jun",
                "date": "2015-11-02",
                "result": 1,
                "id": "tournament_241_191"
            },
            {
                "white": "Lai Zhenen",
                "black": "Hao Xing",
                "date": "2015-11-02",
                "result": 0,
                "id": "tournament_241_192"
            },
            {
                "white": "Hao Hualin",
                "black": "Wu Yishun",
                "date": "2015-11-02",
                "result": 1,
                "id": "tournament_241_193"
            },
            {
                "white": "Fu Qingfang",
                "black": "Chen Xiangke",
                "date": "2015-11-02",
                "result": 1,
                "id": "tournament_241_194"
            },
            {
                "white": "Li Wenzi",
                "black": "Li Youhui",
                "date": "2015-11-02",
                "result": 1,
                "id": "tournament_241_195"
            },
            {
                "white": "Yan Sijun",
                "black": "Zhang Yanying",
                "date": "2015-11-02",
                "result": 0.5,
                "id": "tournament_241_196"
            },
            {
                "white": "Yang Yuxian",
                "black": "Zhang Xu",
                "date": "2015-11-02",
                "result": 0.5,
                "id": "tournament_241_197"
            },
            {
                "white": "Liu Qinxin",
                "black": "Li Tengtian",
                "date": "2015-11-02",
                "result": 0,
                "id": "tournament_241_198"
            },
            {
                "white": "Li Songjiang",
                "black": "Li Linhua",
                "date": "2015-11-02",
                "result": 1,
                "id": "tournament_241_199"
            },
            {
                "white": "Zheng Jianyuan",
                "black": "Wang Jiangji",
                "date": "2015-11-02",
                "result": 1,
                "id": "tournament_241_200"
            },
            {
                "white": "Hu Jianping",
                "black": "Zhao Junzhong",
                "date": "2015-11-02",
                "result": 1,
                "id": "tournament_241_201"
            },
            {
                "white": "Ji Wenfu",
                "black": "Huang Shuchu",
                "date": "2015-11-02",
                "result": 1,
                "id": "tournament_241_202"
            },
            {
                "white": "Hu Shoubiao",
                "black": "Liang Xiaowei",
                "date": "2015-11-02",
                "result": 0,
                "id": "tournament_241_203"
            },
            {
                "white": "Song Shuaihui",
                "black": "Qiao Hongqi",
                "date": "2015-11-02",
                "result": 0.5,
                "id": "tournament_241_204"
            },
            {
                "white": "Bai Xiaoan",
                "black": "Yin Fang",
                "date": "2015-11-02",
                "result": 0.5,
                "id": "tournament_241_205"
            },
            {
                "white": "Liang Meiqiang",
                "black": "Liu Kunhan",
                "date": "2015-11-02",
                "result": 0.5,
                "id": "tournament_241_206"
            },
            {
                "white": "Yang Jing",
                "black": "Xu Baolong",
                "date": "2015-11-02",
                "result": 0,
                "id": "tournament_241_207"
            },
            {
                "white": "Meng Fangquan",
                "black": "Wang Tianbo",
                "date": "2015-11-02",
                "result": 0.5,
                "id": "tournament_241_208"
            },
            {
                "white": "Liu Biyan",
                "black": "Yang Jianxia",
                "date": "2015-11-02",
                "result": 1,
                "id": "tournament_241_209"
            },
            {
                "white": "Lin Xianzhi",
                "black": "He Sipei",
                "date": "2015-11-02",
                "result": 0.5,
                "id": "tournament_241_210"
            }
        ],
        "tour_8": [
            {
                "white": "Li Jianfang",
                "black": "Huang Xing",
                "date": "2015-11-04",
                "result": 0,
                "id": "tournament_241_211"
            },
            {
                "white": "Qiang Haitian",
                "black": "Zhu Zixin",
                "date": "2015-11-04",
                "result": 1,
                "id": "tournament_241_212"
            },
            {
                "white": "Zheng Xuanzhen",
                "black": "Yu Ping",
                "date": "2015-11-04",
                "result": 1,
                "id": "tournament_241_213"
            },
            {
                "white": "Guo Deji",
                "black": "Deng Zhenhua",
                "date": "2015-11-04",
                "result": 0,
                "id": "tournament_241_214"
            },
            {
                "white": "Xie Libo",
                "black": "Feng Xiongmin",
                "date": "2015-11-04",
                "result": 0.5,
                "id": "tournament_241_215"
            },
            {
                "white": "Hu Youbiao",
                "black": "Li Shuchu",
                "date": "2015-11-04",
                "result": 0,
                "id": "tournament_241_216"
            },
            {
                "white": "Xu Ming",
                "black": "Lin Haopeng",
                "date": "2015-11-04",
                "result": 0,
                "id": "tournament_241_217"
            },
            {
                "white": "Li Hai",
                "black": "Hu Qihong",
                "date": "2015-11-04",
                "result": 0.5,
                "id": "tournament_241_218"
            },
            {
                "white": "Chen Chun",
                "black": "Liu Xian",
                "date": "2015-11-04",
                "result": 1,
                "id": "tournament_241_219"
            },
            {
                "white": "Hao Xing",
                "black": "Zhu Xiuyang",
                "date": "2015-11-04",
                "result": 0.5,
                "id": "tournament_241_220"
            },
            {
                "white": "Li Tengtian",
                "black": "Hao Hualin",
                "date": "2015-11-04",
                "result": 0,
                "id": "tournament_241_221"
            },
            {
                "white": "Li Jun",
                "black": "Fu Qingfang",
                "date": "2015-11-04",
                "result": 1,
                "id": "tournament_241_222"
            },
            {
                "white": "Zhang Yanying",
                "black": "Li Wenzi",
                "date": "2015-11-04",
                "result": 0.5,
                "id": "tournament_241_223"
            },
            {
                "white": "Ma Chaofeng",
                "black": "Hao Yong",
                "date": "2015-11-04",
                "result": 0,
                "id": "tournament_241_224"
            },
            {
                "white": "Liang Xiaowei",
                "black": "Yan Sijun",
                "date": "2015-11-04",
                "result": 0.5,
                "id": "tournament_241_225"
            },
            {
                "white": "Wu Yishun",
                "black": "Yang Yuxian",
                "date": "2015-11-04",
                "result": 0.5,
                "id": "tournament_241_226"
            },
            {
                "white": "Zhang Xu",
                "black": "Li Songjiang",
                "date": "2015-11-04",
                "result": 0,
                "id": "tournament_241_227"
            },
            {
                "white": "Li Youhui",
                "black": "Zheng Jianyuan",
                "date": "2015-11-04",
                "result": 1,
                "id": "tournament_241_228"
            },
            {
                "white": "Chen Xiangke",
                "black": "Hu Jianping",
                "date": "2015-11-04",
                "result": 1,
                "id": "tournament_241_229"
            },
            {
                "white": "Li Linhua",
                "black": "Ji Wenfu",
                "date": "2015-11-04",
                "result": 0,
                "id": "tournament_241_230"
            },
            {
                "white": "Qiao Hongqi",
                "black": "Lai Zhenen",
                "date": "2015-11-04",
                "result": 0,
                "id": "tournament_241_231"
            },
            {
                "white": "Yin Fang",
                "black": "Song Shuaihui",
                "date": "2015-11-04",
                "result": 1,
                "id": "tournament_241_232"
            },
            {
                "white": "Xu Baolong",
                "black": "Liu Qinxin",
                "date": "2015-11-04",
                "result": 0,
                "id": "tournament_241_233"
            },
            {
                "white": "Wang Jiangji",
                "black": "Hu Shoubiao",
                "date": "2015-11-04",
                "result": 0,
                "id": "tournament_241_234"
            },
            {
                "white": "Zhao Junzhong",
                "black": "Bai Xiaoan",
                "date": "2015-11-04",
                "result": 0.5,
                "id": "tournament_241_235"
            },
            {
                "white": "Yang Jianxia",
                "black": "Meng Fangquan",
                "date": "2015-11-04",
                "result": 1,
                "id": "tournament_241_236"
            },
            {
                "white": "Huang Shuchu",
                "black": "Liu Biyan",
                "date": "2015-11-04",
                "result": 1,
                "id": "tournament_241_237"
            },
            {
                "white": "Wang Tianbo",
                "black": "Yang Jing",
                "date": "2015-11-04",
                "result": 0,
                "id": "tournament_241_238"
            },
            {
                "white": "Liu Kunhan",
                "black": "Lin Xianzhi",
                "date": "2015-11-04",
                "result": 1,
                "id": "tournament_241_239"
            },
            {
                "white": "He Sipei",
                "black": "Liang Meiqiang",
                "date": "2015-11-04",
                "result": 0.5,
                "id": "tournament_241_240"
            }
        ],
        "tour_9": [
            {
                "white": "Huang Xing",
                "black": "Chen Chun",
                "date": "2015-11-06",
                "result": 1,
                "id": "tournament_241_241"
            },
            {
                "white": "Li Shuchu",
                "black": "Qiang Haitian",
                "date": "2015-11-06",
                "result": 0.5,
                "id": "tournament_241_242"
            },
            {
                "white": "Deng Zhenhua",
                "black": "Li Jianfang",
                "date": "2015-11-06",
                "result": 1,
                "id": "tournament_241_243"
            },
            {
                "white": "Lin Haopeng",
                "black": "Xie Libo",
                "date": "2015-11-06",
                "result": 0.5,
                "id": "tournament_241_244"
            },
            {
                "white": "Zhu Zixin",
                "black": "Xu Ming",
                "date": "2015-11-06",
                "result": 1,
                "id": "tournament_241_245"
            },
            {
                "white": "Yu Ping",
                "black": "Guo Deji",
                "date": "2015-11-06",
                "result": 0,
                "id": "tournament_241_246"
            },
            {
                "white": "Feng Xiongmin",
                "black": "Zheng Xuanzhen",
                "date": "2015-11-06",
                "result": 0.5,
                "id": "tournament_241_247"
            },
            {
                "white": "Hu Qihong",
                "black": "Hao Xing",
                "date": "2015-11-06",
                "result": 0.5,
                "id": "tournament_241_248"
            },
            {
                "white": "Hao Hualin",
                "black": "Hu Youbiao",
                "date": "2015-11-06",
                "result": 1,
                "id": "tournament_241_249"
            },
            {
                "white": "Zhu Xiuyang",
                "black": "Li Hai",
                "date": "2015-11-06",
                "result": 1,
                "id": "tournament_241_250"
            },
            {
                "white": "Li Wenzi",
                "black": "Li Jun",
                "date": "2015-11-06",
                "result": 0,
                "id": "tournament_241_251"
            },
            {
                "white": "Hao Yong",
                "black": "Zhang Yanying",
                "date": "2015-11-06",
                "result": 1,
                "id": "tournament_241_252"
            },
            {
                "white": "Li Songjiang",
                "black": "Li Tengtian",
                "date": "2015-11-06",
                "result": 0.5,
                "id": "tournament_241_253"
            },
            {
                "white": "Ji Wenfu",
                "black": "Chen Xiangke",
                "date": "2015-11-06",
                "result": 0.5,
                "id": "tournament_241_254"
            },
            {
                "white": "Liu Xian",
                "black": "Liang Xiaowei",
                "date": "2015-11-06",
                "result": 0.5,
                "id": "tournament_241_255"
            },
            {
                "white": "Fu Qingfang",
                "black": "Li Youhui",
                "date": "2015-11-06",
                "result": 1,
                "id": "tournament_241_256"
            },
            {
                "white": "Yan Sijun",
                "black": "Ma Chaofeng",
                "date": "2015-11-06",
                "result": 1,
                "id": "tournament_241_257"
            },
            {
                "white": "Yang Yuxian",
                "black": "Liu Kunhan",
                "date": "2015-11-06",
                "result": 1,
                "id": "tournament_241_258"
            },
            {
                "white": "Lai Zhenen",
                "black": "Yin Fang",
                "date": "2015-11-06",
                "result": 1,
                "id": "tournament_241_259"
            },
            {
                "white": "Zheng Jianyuan",
                "black": "Zhang Xu",
                "date": "2015-11-06",
                "result": 0,
                "id": "tournament_241_260"
            },
            {
                "white": "Hu Jianping",
                "black": "Wu Yishun",
                "date": "2015-11-06",
                "result": 1,
                "id": "tournament_241_261"
            },
            {
                "white": "Liu Qinxin",
                "black": "Huang Shuchu",
                "date": "2015-11-06",
                "result": 0.5,
                "id": "tournament_241_262"
            },
            {
                "white": "Hu Shoubiao",
                "black": "Qiao Hongqi",
                "date": "2015-11-06",
                "result": 1,
                "id": "tournament_241_263"
            },
            {
                "white": "Song Shuaihui",
                "black": "Li Linhua",
                "date": "2015-11-06",
                "result": 0.5,
                "id": "tournament_241_264"
            },
            {
                "white": "Bai Xiaoan",
                "black": "He Sipei",
                "date": "2015-11-06",
                "result": 0,
                "id": "tournament_241_265"
            },
            {
                "white": "Meng Fangquan",
                "black": "Xu Baolong",
                "date": "2015-11-06",
                "result": 0.5,
                "id": "tournament_241_266"
            },
            {
                "white": "Liang Meiqiang",
                "black": "Wang Tianbo",
                "date": "2015-11-06",
                "result": 0.5,
                "id": "tournament_241_267"
            },
            {
                "white": "Yang Jing",
                "black": "Wang Jiangji",
                "date": "2015-11-06",
                "result": 0.5,
                "id": "tournament_241_268"
            },
            {
                "white": "Liu Biyan",
                "black": "Zhao Junzhong",
                "date": "2015-11-06",
                "result": 0.5,
                "id": "tournament_241_269"
            },
            {
                "white": "Lin Xianzhi",
                "black": "Yang Jianxia",
                "date": "2015-11-06",
                "result": 0.5,
                "id": "tournament_241_270"
            }
        ],
        "tour_10": [
            {
                "white": "Li Jun",
                "black": "Huang Xing",
                "date": "2015-11-08",
                "result": 0.5,
                "id": "tournament_241_271"
            },
            {
                "white": "Qiang Haitian",
                "black": "Lin Haopeng",
                "date": "2015-11-08",
                "result": 1,
                "id": "tournament_241_272"
            },
            {
                "white": "Chen Chun",
                "black": "Deng Zhenhua",
                "date": "2015-11-08",
                "result": 0,
                "id": "tournament_241_273"
            },
            {
                "white": "Xie Libo",
                "black": "Li Shuchu",
                "date": "2015-11-08",
                "result": 0.5,
                "id": "tournament_241_274"
            },
            {
                "white": "Li Jianfang",
                "black": "Zhu Zixin",
                "date": "2015-11-08",
                "result": 0.5,
                "id": "tournament_241_275"
            },
            {
                "white": "Guo Deji",
                "black": "Hao Hualin",
                "date": "2015-11-08",
                "result": 0.5,
                "id": "tournament_241_276"
            },
            {
                "white": "Xu Ming",
                "black": "Feng Xiongmin",
                "date": "2015-11-08",
                "result": 0.5,
                "id": "tournament_241_277"
            },
            {
                "white": "Li Tengtian",
                "black": "Hu Qihong",
                "date": "2015-11-08",
                "result": 0.5,
                "id": "tournament_241_278"
            },
            {
                "white": "Zheng Xuanzhen",
                "black": "Zhu Xiuyang",
                "date": "2015-11-08",
                "result": 1,
                "id": "tournament_241_279"
            },
            {
                "white": "Hao Xing",
                "black": "Hao Yong",
                "date": "2015-11-08",
                "result": 1,
                "id": "tournament_241_280"
            },
            {
                "white": "Hu Youbiao",
                "black": "Yu Ping",
                "date": "2015-11-08",
                "result": 0.5,
                "id": "tournament_241_281"
            },
            {
                "white": "Liang Xiaowei",
                "black": "Li Songjiang",
                "date": "2015-11-08",
                "result": 0.5,
                "id": "tournament_241_282"
            },
            {
                "white": "Li Hai",
                "black": "Ji Wenfu",
                "date": "2015-11-08",
                "result": 1,
                "id": "tournament_241_283"
            },
            {
                "white": "Zhang Yanying",
                "black": "Fu Qingfang",
                "date": "2015-11-08",
                "result": 0.5,
                "id": "tournament_241_284"
            },
            {
                "white": "Chen Xiangke",
                "black": "Yan Sijun",
                "date": "2015-11-08",
                "result": 1,
                "id": "tournament_241_285"
            },
            {
                "white": "Li Youhui",
                "black": "Yang Yuxian",
                "date": "2015-11-08",
                "result": 0,
                "id": "tournament_241_286"
            },
            {
                "white": "Zhang Xu",
                "black": "Lai Zhenen",
                "date": "2015-11-08",
                "result": 0,
                "id": "tournament_241_287"
            },
            {
                "white": "Yin Fang",
                "black": "Li Wenzi",
                "date": "2015-11-08",
                "result": 0,
                "id": "tournament_241_288"
            },
            {
                "white": "Huang Shuchu",
                "black": "Liu Xian",
                "date": "2015-11-08",
                "result": 0,
                "id": "tournament_241_289"
            },
            {
                "white": "He Sipei",
                "black": "Hu Jianping",
                "date": "2015-11-08",
                "result": 0.5,
                "id": "tournament_241_290"
            },
            {
                "white": "Ma Chaofeng",
                "black": "Hu Shoubiao",
                "date": "2015-11-08",
                "result": 1,
                "id": "tournament_241_291"
            },
            {
                "white": "Wu Yishun",
                "black": "Liu Qinxin",
                "date": "2015-11-08",
                "result": 0.5,
                "id": "tournament_241_292"
            },
            {
                "white": "Yang Jianxia",
                "black": "Xu Baolong",
                "date": "2015-11-08",
                "result": 1,
                "id": "tournament_241_293"
            },
            {
                "white": "Qiao Hongqi",
                "black": "Bai Xiaoan",
                "date": "2015-11-08",
                "result": 0.5,
                "id": "tournament_241_294"
            },
            {
                "white": "Wang Jiangji",
                "black": "Liu Biyan",
                "date": "2015-11-08",
                "result": 1,
                "id": "tournament_241_295"
            },
            {
                "white": "Li Linhua",
                "black": "Zheng Jianyuan",
                "date": "2015-11-08",
                "result": 0,
                "id": "tournament_241_296"
            },
            {
                "white": "Meng Fangquan",
                "black": "Liang Meiqiang",
                "date": "2015-11-08",
                "result": 1,
                "id": "tournament_241_297"
            },
            {
                "white": "Zhao Junzhong",
                "black": "Song Shuaihui",
                "date": "2015-11-08",
                "result": 0.5,
                "id": "tournament_241_298"
            },
            {
                "white": "Lin Xianzhi",
                "black": "Yang Jing",
                "date": "2015-11-08",
                "result": 0,
                "id": "tournament_241_299"
            },
            {
                "white": "Liu Kunhan",
                "black": "Wang Tianbo",
                "date": "2015-11-08",
                "result": 0.5,
                "id": "tournament_241_300"
            }
        ],
        "tour_11": [
            {
                "white": "Huang Xing",
                "black": "Chen Xiangke",
                "date": "2015-11-10",
                "result": 1,
                "id": "tournament_241_301"
            },
            {
                "white": "Hao Hualin",
                "black": "Qiang Haitian",
                "date": "2015-11-10",
                "result": 1,
                "id": "tournament_241_302"
            },
            {
                "white": "Deng Zhenhua",
                "black": "Hao Xing",
                "date": "2015-11-10",
                "result": 0.5,
                "id": "tournament_241_303"
            },
            {
                "white": "Li Shuchu",
                "black": "Zheng Xuanzhen",
                "date": "2015-11-10",
                "result": 0,
                "id": "tournament_241_304"
            },
            {
                "white": "Zhu Zixin",
                "black": "Li Jun",
                "date": "2015-11-10",
                "result": 0.5,
                "id": "tournament_241_305"
            },
            {
                "white": "Lin Haopeng",
                "black": "Guo Deji",
                "date": "2015-11-10",
                "result": 1,
                "id": "tournament_241_306"
            },
            {
                "white": "Feng Xiongmin",
                "black": "Chen Chun",
                "date": "2015-11-10",
                "result": 0.5,
                "id": "tournament_241_307"
            },
            {
                "white": "Hu Qihong",
                "black": "Xie Libo",
                "date": "2015-11-10",
                "result": 1,
                "id": "tournament_241_308"
            },
            {
                "white": "Yang Yuxian",
                "black": "Li Hai",
                "date": "2015-11-10",
                "result": 0,
                "id": "tournament_241_309"
            },
            {
                "white": "Lai Zhenen",
                "black": "Li Jianfang",
                "date": "2015-11-10",
                "result": 0.5,
                "id": "tournament_241_310"
            },
            {
                "white": "Zhu Xiuyang",
                "black": "Hu Youbiao",
                "date": "2015-11-10",
                "result": 0,
                "id": "tournament_241_311"
            },
            {
                "white": "Hao Yong",
                "black": "Xu Ming",
                "date": "2015-11-10",
                "result": 0.5,
                "id": "tournament_241_312"
            },
            {
                "white": "Yu Ping",
                "black": "Li Tengtian",
                "date": "2015-11-10",
                "result": 0.5,
                "id": "tournament_241_313"
            },
            {
                "white": "Li Songjiang",
                "black": "He Sipei",
                "date": "2015-11-10",
                "result": 1,
                "id": "tournament_241_314"
            },
            {
                "white": "Fu Qingfang",
                "black": "Liang Xiaowei",
                "date": "2015-11-10",
                "result": 0.5,
                "id": "tournament_241_315"
            },
            {
                "white": "Li Wenzi",
                "black": "Yang Jianxia",
                "date": "2015-11-10",
                "result": 1,
                "id": "tournament_241_316"
            },
            {
                "white": "Liu Xian",
                "black": "Zhang Yanying",
                "date": "2015-11-10",
                "result": 1,
                "id": "tournament_241_317"
            },
            {
                "white": "Ji Wenfu",
                "black": "Ma Chaofeng",
                "date": "2015-11-10",
                "result": 1,
                "id": "tournament_241_318"
            },
            {
                "white": "Yan Sijun",
                "black": "Huang Shuchu",
                "date": "2015-11-10",
                "result": 1,
                "id": "tournament_241_319"
            },
            {
                "white": "Hu Jianping",
                "black": "Zhang Xu",
                "date": "2015-11-10",
                "result": 1,
                "id": "tournament_241_320"
            },
            {
                "white": "Hu Shoubiao",
                "black": "Li Youhui",
                "date": "2015-11-10",
                "result": 0,
                "id": "tournament_241_321"
            },
            {
                "white": "Liu Qinxin",
                "black": "Yin Fang",
                "date": "2015-11-10",
                "result": 1,
                "id": "tournament_241_322"
            },
            {
                "white": "Zheng Jianyuan",
                "black": "Wu Yishun",
                "date": "2015-11-10",
                "result": 0,
                "id": "tournament_241_323"
            },
            {
                "white": "Yang Jing",
                "black": "Liu Kunhan",
                "date": "2015-11-10",
                "result": 1,
                "id": "tournament_241_324"
            },
            {
                "white": "Lin Xianzhi",
                "black": "Wang Tianbo",
                "date": "2015-11-10",
                "result": 0.5,
                "id": "tournament_241_325"
            },
            {
                "white": "Qiao Hongqi",
                "black": "Xu Baolong",
                "date": "2015-11-10",
                "result": 0,
                "id": "tournament_241_326"
            },
            {
                "white": "Song Shuaihui",
                "black": "Meng Fangquan",
                "date": "2015-11-10",
                "result": 1,
                "id": "tournament_241_327"
            },
            {
                "white": "Liang Meiqiang",
                "black": "Wang Jiangji",
                "date": "2015-11-10",
                "result": 0.5,
                "id": "tournament_241_328"
            },
            {
                "white": "Li Linhua",
                "black": "Zhao Junzhong",
                "date": "2015-11-10",
                "result": 1,
                "id": "tournament_241_329"
            },
            {
                "white": "Bai Xiaoan",
                "black": "Liu Biyan",
                "date": "2015-11-10",
                "result": 1,
                "id": "tournament_241_330"
            }
        ],
        "tour_12": [
            {
                "white": "Hu Youbiao",
                "black": "Huang Xing",
                "date": "2015-11-12",
                "result": 0,
                "id": "tournament_241_331"
            },
            {
                "white": "Chen Xiangke",
                "black": "Deng Zhenhua",
                "date": "2015-11-12",
                "result": 0.5,
                "id": "tournament_241_332"
            },
            {
                "white": "Qiang Haitian",
                "black": "Lai Zhenen",
                "date": "2015-11-12",
                "result": 1,
                "id": "tournament_241_333"
            },
            {
                "white": "Xie Libo",
                "black": "Hao Hualin",
                "date": "2015-11-12",
                "result": 0,
                "id": "tournament_241_334"
            },
            {
                "white": "Li Hai",
                "black": "Zhu Zixin",
                "date": "2015-11-12",
                "result": 0.5,
                "id": "tournament_241_335"
            },
            {
                "white": "Hao Xing",
                "black": "Lin Haopeng",
                "date": "2015-11-12",
                "result": 1,
                "id": "tournament_241_336"
            },
            {
                "white": "Guo Deji",
                "black": "Hu Qihong",
                "date": "2015-11-12",
                "result": 0.5,
                "id": "tournament_241_337"
            },
            {
                "white": "Zheng Xuanzhen",
                "black": "Li Songjiang",
                "date": "2015-11-12",
                "result": 1,
                "id": "tournament_241_338"
            },
            {
                "white": "Li Jun",
                "black": "Li Shuchu",
                "date": "2015-11-12",
                "result": 0.5,
                "id": "tournament_241_339"
            },
            {
                "white": "Li Tengtian",
                "black": "Feng Xiongmin",
                "date": "2015-11-12",
                "result": 0.5,
                "id": "tournament_241_340"
            },
            {
                "white": "Chen Chun",
                "black": "Li Wenzi",
                "date": "2015-11-12",
                "result": 1,
                "id": "tournament_241_341"
            },
            {
                "white": "Li Jianfang",
                "black": "Liu Xian",
                "date": "2015-11-12",
                "result": 1,
                "id": "tournament_241_342"
            },
            {
                "white": "Xu Ming",
                "black": "Yang Yuxian",
                "date": "2015-11-12",
                "result": 0,
                "id": "tournament_241_343"
            },
            {
                "white": "Liang Xiaowei",
                "black": "Hao Yong",
                "date": "2015-11-12",
                "result": 0,
                "id": "tournament_241_344"
            },
            {
                "white": "Li Youhui",
                "black": "Yu Ping",
                "date": "2015-11-12",
                "result": 0.5,
                "id": "tournament_241_345"
            },
            {
                "white": "Wu Yishun",
                "black": "Fu Qingfang",
                "date": "2015-11-12",
                "result": 1,
                "id": "tournament_241_346"
            },
            {
                "white": "Zhang Yanying",
                "black": "Ji Wenfu",
                "date": "2015-11-12",
                "result": 0.5,
                "id": "tournament_241_347"
            },
            {
                "white": "He Sipei",
                "black": "Yan Sijun",
                "date": "2015-11-12",
                "result": 0,
                "id": "tournament_241_348"
            },
            {
                "white": "Ma Chaofeng",
                "black": "Hu Jianping",
                "date": "2015-11-12",
                "result": 0.5,
                "id": "tournament_241_349"
            },
            {
                "white": "Zhang Xu",
                "black": "Zhu Xiuyang",
                "date": "2015-11-12",
                "result": 0,
                "id": "tournament_241_350"
            },
            {
                "white": "Yang Jianxia",
                "black": "Liu Qinxin",
                "date": "2015-11-12",
                "result": 0,
                "id": "tournament_241_351"
            },
            {
                "white": "Li Linhua",
                "black": "Yang Jing",
                "date": "2015-11-12",
                "result": 0.5,
                "id": "tournament_241_352"
            },
            {
                "white": "Xu Baolong",
                "black": "Song Shuaihui",
                "date": "2015-11-12",
                "result": 0.5,
                "id": "tournament_241_353"
            },
            {
                "white": "Yin Fang",
                "black": "Hu Shoubiao",
                "date": "2015-11-12",
                "result": 0,
                "id": "tournament_241_354"
            },
            {
                "white": "Huang Shuchu",
                "black": "Zheng Jianyuan",
                "date": "2015-11-12",
                "result": 0.5,
                "id": "tournament_241_355"
            },
            {
                "white": "Wang Tianbo",
                "black": "Bai Xiaoan",
                "date": "2015-11-12",
                "result": 0,
                "id": "tournament_241_356"
            },
            {
                "white": "Qiao Hongqi",
                "black": "Liang Meiqiang",
                "date": "2015-11-12",
                "result": 0.5,
                "id": "tournament_241_357"
            },
            {
                "white": "Wang Jiangji",
                "black": "Lin Xianzhi",
                "date": "2015-11-12",
                "result": 0.5,
                "id": "tournament_241_358"
            },
            {
                "white": "Liu Kunhan",
                "black": "Liu Biyan",
                "date": "2015-11-12",
                "result": 1,
                "id": "tournament_241_359"
            },
            {
                "white": "Zhao Junzhong",
                "black": "Meng Fangquan",
                "date": "2015-11-12",
                "result": 1,
                "id": "tournament_241_360"
            }
        ],
        "tour_13": [
            {
                "white": "Huang Xing",
                "black": "Li Tengtian",
                "date": "2015-11-14",
                "result": 1,
                "id": "tournament_241_361"
            },
            {
                "white": "Deng Zhenhua",
                "black": "Hu Youbiao",
                "date": "2015-11-14",
                "result": 0.5,
                "id": "tournament_241_362"
            },
            {
                "white": "Yang Yuxian",
                "black": "Qiang Haitian",
                "date": "2015-11-14",
                "result": 1,
                "id": "tournament_241_363"
            },
            {
                "white": "Hao Hualin",
                "black": "Hao Xing",
                "date": "2015-11-14",
                "result": 0.5,
                "id": "tournament_241_364"
            },
            {
                "white": "Hao Yong",
                "black": "Zheng Xuanzhen",
                "date": "2015-11-14",
                "result": 0.5,
                "id": "tournament_241_365"
            },
            {
                "white": "Zhu Zixin",
                "black": "Chen Chun",
                "date": "2015-11-14",
                "result": 1,
                "id": "tournament_241_366"
            },
            {
                "white": "Hu Qihong",
                "black": "Li Jianfang",
                "date": "2015-11-14",
                "result": 1,
                "id": "tournament_241_367"
            },
            {
                "white": "Lin Haopeng",
                "black": "Li Hai",
                "date": "2015-11-14",
                "result": 0,
                "id": "tournament_241_368"
            },
            {
                "white": "Li Shuchu",
                "black": "Guo Deji",
                "date": "2015-11-14",
                "result": 1,
                "id": "tournament_241_369"
            },
            {
                "white": "Feng Xiongmin",
                "black": "Li Jun",
                "date": "2015-11-14",
                "result": 0.5,
                "id": "tournament_241_370"
            },
            {
                "white": "Yan Sijun",
                "black": "Xie Libo",
                "date": "2015-11-14",
                "result": 1,
                "id": "tournament_241_371"
            },
            {
                "white": "Lai Zhenen",
                "black": "Xu Ming",
                "date": "2015-11-14",
                "result": 0.5,
                "id": "tournament_241_372"
            },
            {
                "white": "Li Songjiang",
                "black": "Chen Xiangke",
                "date": "2015-11-14",
                "result": 0,
                "id": "tournament_241_373"
            },
            {
                "white": "Li Wenzi",
                "black": "Wu Yishun",
                "date": "2015-11-14",
                "result": 0.5,
                "id": "tournament_241_374"
            },
            {
                "white": "Liu Xian",
                "black": "Li Youhui",
                "date": "2015-11-14",
                "result": 1,
                "id": "tournament_241_375"
            },
            {
                "white": "Yu Ping",
                "black": "Zhang Yanying",
                "date": "2015-11-14",
                "result": 0.5,
                "id": "tournament_241_376"
            },
            {
                "white": "Ji Wenfu",
                "black": "Wang Jiangji",
                "date": "2015-11-14",
                "result": 1,
                "id": "tournament_241_377"
            },
            {
                "white": "Hu Jianping",
                "black": "Li Linhua",
                "date": "2015-11-14",
                "result": 1,
                "id": "tournament_241_378"
            },
            {
                "white": "Zhu Xiuyang",
                "black": "Liang Xiaowei",
                "date": "2015-11-14",
                "result": 1,
                "id": "tournament_241_379"
            },
            {
                "white": "Liu Qinxin",
                "black": "Zhao Junzhong",
                "date": "2015-11-14",
                "result": 1,
                "id": "tournament_241_380"
            },
            {
                "white": "Fu Qingfang",
                "black": "Xu Baolong",
                "date": "2015-11-14",
                "result": 0.5,
                "id": "tournament_241_381"
            },
            {
                "white": "Yang Jing",
                "black": "Ma Chaofeng",
                "date": "2015-11-14",
                "result": 1,
                "id": "tournament_241_382"
            },
            {
                "white": "Song Shuaihui",
                "black": "Liu Kunhan",
                "date": "2015-11-14",
                "result": 0.5,
                "id": "tournament_241_383"
            },
            {
                "white": "Lin Xianzhi",
                "black": "Meng Fangquan",
                "date": "2015-11-14",
                "result": 0.5,
                "id": "tournament_241_384"
            },
            {
                "white": "Zheng Jianyuan",
                "black": "Qiao Hongqi",
                "date": "2015-11-14",
                "result": 0.5,
                "id": "tournament_241_385"
            },
            {
                "white": "Zhang Xu",
                "black": "Yin Fang",
                "date": "2015-11-14",
                "result": 0,
                "id": "tournament_241_386"
            },
            {
                "white": "Liu Biyan",
                "black": "Liang Meiqiang",
                "date": "2015-11-14",
                "result": 0,
                "id": "tournament_241_387"
            },
            {
                "white": "Hu Shoubiao",
                "black": "He Sipei",
                "date": "2015-11-14",
                "result": 0.5,
                "id": "tournament_241_388"
            },
            {
                "white": "Bai Xiaoan",
                "black": "Huang Shuchu",
                "date": "2015-11-14",
                "result": 0.5,
                "id": "tournament_241_389"
            },
            {
                "white": "Yang Jianxia",
                "black": "Wang Tianbo",
                "date": "2015-11-14",
                "result": 1,
                "id": "tournament_241_390"
            }
        ]
    },
    "tours": 13,
    "time_control": "rapid"
}